rheostatic/__init__.py
rheostatic/__main__.py
rheostatic/base.py
rheostatic/server.py
rheostatic/utils.py
rheostatic/tests/__init__.py
rheostatic/tests/test_cli.py
rheostatic/tests/test_responces.py
rheostatic/tests/data/404.html
rheostatic/tests/data/favicon.ico
rheostatic/tests/data/index.html
rheostatic/tests/data/other.html
rheostatic/tests/data/subdir/expected_dir_list.html
rheostatic/tests/data/subdir/link_to_subpage.html
rheostatic/tests/data/subdir/subpage.html
rheostatic/tests/data/subdir/unknown-file-type.abc
Rheostatic-0.0.2.dist-info/LICENSE
Rheostatic-0.0.2.dist-info/METADATA
Rheostatic-0.0.2.dist-info/WHEEL
Rheostatic-0.0.2.dist-info/entry_points.txt
Rheostatic-0.0.2.dist-info/top_level.txt
Rheostatic-0.0.2.dist-info/RECORD
